bombaysoftwares_pysupp/__init__.py
bombaysoftwares_pysupp/utils.py
bombaysoftwares_pysupp-1.0.5.dist-info/LICENSE
bombaysoftwares_pysupp-1.0.5.dist-info/METADATA
bombaysoftwares_pysupp-1.0.5.dist-info/WHEEL
bombaysoftwares_pysupp-1.0.5.dist-info/top_level.txt
bombaysoftwares_pysupp-1.0.5.dist-info/RECORD
