Metadata-Version: 2.1
Name: bombaysoftwares-pysupp
Version: 1.0.5
Summary: The bombaysoftwares_pysupp package provides a comprehensive set of utility functions for various operations in Python. These functions simplify common tasks such as date formatting, timestamp conversion, manipulating strings. This package is designed to enhance the functionality of various operations in your Python projects.
Home-page: UNKNOWN
Author: Bombay Softwares
License: MIT
Project-URL: Bug Tracker, https://github.com/Edugem-Technologies/bombaysoftwares-pysupp/issues
Project-URL: Source Code, https://github.com/Edugem-Technologies/bombaysoftwares-pysupp
Project-URL: Documentation, https://github.com/Edugem-Technologies/bombaysoftwares-pysupp#readme
Platform: UNKNOWN
Classifier: Development Status :: 5 - Production/Stable
Classifier: Intended Audience :: Developers
Classifier: Programming Language :: Python
Classifier: Programming Language :: Python :: 3.6
Classifier: Programming Language :: Python :: 3.8
Classifier: License :: OSI Approved :: MIT License
Classifier: Topic :: Software Development
Classifier: Topic :: Scientific/Engineering
Classifier: Operating System :: OS Independent
Requires-Dist: PyJWT
Requires-Dist: hashids
Requires-Dist: python-dateutil
Requires-Dist: python-slugify
Requires-Dist: six
Requires-Dist: text-unidecode
Requires-Dist: pytz
